cyb600_lab1_1-2.0.data/scripts/cyb_datetime.py
cyb600_lab1_1-2.0.data/scripts/datetime.py
cyb600_sd/__init__.py
cyb600_sd/current_time.py
cyb600_lab1_1-2.0.dist-info/METADATA
cyb600_lab1_1-2.0.dist-info/WHEEL
cyb600_lab1_1-2.0.dist-info/top_level.txt
cyb600_lab1_1-2.0.dist-info/RECORD
