Metadata-Version: 2.1
Name: cyb600-lab1-1
Version: 2.0
Summary: UNKNOWN
Home-page: UNKNOWN
Author: Siobhan Dougherty
Author-email: doughers@canisius.edu
License: Apache License Version 2.0
Platform: UNKNOWN
Requires-Dist: Flask
